[{"idVuelo":"VL16553","aeronave":{"placa":"fds","tipo":3,"COMERCIAL":1,"CARGA":2,"AVIONETA":3,"estado":3},"aeropuertoOrigen":{"nombre":"Aeropuerto Internacional Tobías Bolaños"},"aeropuertoDestino":{"pistas":[{"disponible":true,"numPista":1},{"disponible":true,"numPista":2}],"puertas":[{"numPuerta":1,"disponible":true,"companiaAerea":{"nombre":"AVIANCA"}},{"numPuerta":2,"disponible":true,"companiaAerea":{"nombre":"IBERIA"}},{"numPuerta":3,"disponible":true,"companiaAerea":{"nombre":"TACA"}},{"numPuerta":4,"disponible":true,"companiaAerea":{"nombre":"AVIANCA"}}],"nombre":"Juan Santamaría"},"companiaAerea":{"nombre":"Avianca"},"horaSalida":"06:00:14","horaLlegada":"01:00:30"},{"idVuelo":"VL80340","aeronave":{"placa":"asd","tipo":3,"COMERCIAL":1,"CARGA":2,"AVIONETA":3,"estado":3},"aeropuertoOrigen":{"nombre":"Aeropuerto de Bruselas-National"},"aeropuertoDestino":{"pistas":[{"disponible":true,"numPista":1},{"disponible":true,"numPista":2}],"puertas":[{"numPuerta":1,"disponible":true,"companiaAerea":{"nombre":"AVIANCA"}},{"numPuerta":2,"disponible":true,"companiaAerea":{"nombre":"IBERIA"}},{"numPuerta":3,"disponible":true,"companiaAerea":{"nombre":"TACA"}},{"numPuerta":4,"disponible":true,"companiaAerea":{"nombre":"AVIANCA"}}],"nombre":"Juan Santamaría"},"companiaAerea":{"nombre":"Iberia"},"horaSalida":"11:38:37","horaLlegada":"01:38:55"},{"idVuelo":"VL80340","aeronave":{"placa":"asd","tipo":3,"COMERCIAL":1,"CARGA":2,"AVIONETA":3,"estado":1},"aeropuertoOrigen":{"nombre":"Aeropuerto de Bruselas-National"},"aeropuertoDestino":{"pistas":[{"disponible":true,"numPista":1},{"disponible":true,"numPista":2}],"puertas":[{"numPuerta":1,"disponible":true,"companiaAerea":{"nombre":"AVIANCA"}},{"numPuerta":2,"disponible":true,"companiaAerea":{"nombre":"IBERIA"}},{"numPuerta":3,"disponible":true,"companiaAerea":{"nombre":"TACA"}},{"numPuerta":4,"disponible":true,"companiaAerea":{"nombre":"AVIANCA"}}],"nombre":"Juan Santamaría"},"companiaAerea":{"nombre":"Iberia"},"horaSalida":"11:38:37","horaLlegada":"01:39:09"},{"idVuelo":"VL04923","aeronave":{"placa":"asdf","tipo":1,"COMERCIAL":1,"CARGA":2,"AVIONETA":3,"estado":3},"aeropuertoOrigen":{"nombre":"Aeropuerto Internacional de Viena"},"aeropuertoDestino":{"pistas":[{"disponible":true,"numPista":1},{"disponible":true,"numPista":2}],"puertas":[{"numPuerta":1,"disponible":true,"companiaAerea":{"nombre":"AVIANCA"}},{"numPuerta":2,"disponible":true,"companiaAerea":{"nombre":"IBERIA"}},{"numPuerta":3,"disponible":true,"companiaAerea":{"nombre":"TACA"}},{"numPuerta":4,"disponible":true,"companiaAerea":{"nombre":"AVIANCA"}}],"nombre":"Juan Santamaría"},"companiaAerea":{"nombre":"Iberia"},"horaSalida":"21:42:04","horaLlegada":"01:42:17"},{"idVuelo":"VL04923","aeronave":{"placa":"asdf","tipo":1,"COMERCIAL":1,"CARGA":2,"AVIONETA":3,"estado":1},"aeropuertoOrigen":{"nombre":"Aeropuerto Internacional de Viena"},"aeropuertoDestino":{"pistas":[{"disponible":true,"numPista":1},{"disponible":true,"numPista":2}],"puertas":[{"numPuerta":1,"disponible":true,"companiaAerea":{"nombre":"AVIANCA"}},{"numPuerta":2,"disponible":true,"companiaAerea":{"nombre":"IBERIA"}},{"numPuerta":3,"disponible":true,"companiaAerea":{"nombre":"TACA"}},{"numPuerta":4,"disponible":true,"companiaAerea":{"nombre":"AVIANCA"}}],"nombre":"Juan Santamaría"},"companiaAerea":{"nombre":"Iberia"},"horaSalida":"21:42:04","horaLlegada":"01:42:26"},{"idVuelo":"VL52452","aeronave":{"placa":"1236534","tipo":3,"COMERCIAL":1,"CARGA":2,"AVIONETA":3,"estado":3},"aeropuertoOrigen":{"nombre":"Aeropuerto de Bruselas-National"},"aeropuertoDestino":{"pistas":[{"disponible":true,"numPista":1},{"disponible":true,"numPista":2}],"puertas":[{"numPuerta":1,"disponible":true,"companiaAerea":{"nombre":"AVIANCA"}},{"numPuerta":2,"disponible":true,"companiaAerea":{"nombre":"IBERIA"}},{"numPuerta":3,"disponible":true,"companiaAerea":{"nombre":"TACA"}},{"numPuerta":4,"disponible":true,"companiaAerea":{"nombre":"AVIANCA"}}],"nombre":"Juan Santamaría"},"companiaAerea":{"nombre":"Avianca"},"horaSalida":"13:43:33","horaLlegada":"01:44:11"},{"idVuelo":"VL52452","aeronave":{"placa":"1236534","tipo":3,"COMERCIAL":1,"CARGA":2,"AVIONETA":3,"estado":1},"aeropuertoOrigen":{"nombre":"Aeropuerto de Bruselas-National"},"aeropuertoDestino":{"pistas":[{"disponible":true,"numPista":1},{"disponible":true,"numPista":2}],"puertas":[{"numPuerta":1,"disponible":true,"companiaAerea":{"nombre":"AVIANCA"}},{"numPuerta":2,"disponible":true,"companiaAerea":{"nombre":"IBERIA"}},{"numPuerta":3,"disponible":true,"companiaAerea":{"nombre":"TACA"}},{"numPuerta":4,"disponible":true,"companiaAerea":{"nombre":"AVIANCA"}}],"nombre":"Juan Santamaría"},"companiaAerea":{"nombre":"Avianca"},"horaSalida":"13:43:33","horaLlegada":"01:44:12"},{"idVuelo":"VL52452","aeronave":{"placa":"1236534","tipo":3,"COMERCIAL":1,"CARGA":2,"AVIONETA":3,"estado":1},"aeropuertoOrigen":{"nombre":"Aeropuerto de Bruselas-National"},"aeropuertoDestino":{"pistas":[{"disponible":true,"numPista":1},{"disponible":true,"numPista":2}],"puertas":[{"numPuerta":1,"disponible":true,"companiaAerea":{"nombre":"AVIANCA"}},{"numPuerta":2,"disponible":true,"companiaAerea":{"nombre":"IBERIA"}},{"numPuerta":3,"disponible":true,"companiaAerea":{"nombre":"TACA"}},{"numPuerta":4,"disponible":true,"companiaAerea":{"nombre":"AVIANCA"}}],"nombre":"Juan Santamaría"},"companiaAerea":{"nombre":"Avianca"},"horaSalida":"13:43:33","horaLlegada":"01:44:12"},{"idVuelo":"VL80340","aeronave":{"placa":"fds","tipo":1,"COMERCIAL":1,"CARGA":2,"AVIONETA":3,"estado":3},"aeropuertoOrigen":{"nombre":"Aeropuerto Internacional Tobías Bolaños"},"aeropuertoDestino":{"pistas":[{"disponible":true,"numPista":1},{"disponible":true,"numPista":2}],"puertas":[{"numPuerta":1,"disponible":true,"companiaAerea":{"nombre":"AVIANCA"}},{"numPuerta":2,"disponible":true,"companiaAerea":{"nombre":"IBERIA"}},{"numPuerta":3,"disponible":true,"companiaAerea":{"nombre":"TACA"}},{"numPuerta":4,"disponible":true,"companiaAerea":{"nombre":"AVIANCA"}}],"nombre":"Juan Santamaría"},"companiaAerea":{"nombre":"Iberia"},"horaSalida":"04:57:08","horaLlegada":"01:57:12"},{"idVuelo":"VL96734","aeronave":{"placa":"123asdf","tipo":1,"COMERCIAL":1,"CARGA":2,"AVIONETA":3,"estado":3},"aeropuertoOrigen":{"nombre":"Aeropuerto de Hamburgo"},"aeropuertoDestino":{"pistas":[{"disponible":true,"numPista":1},{"disponible":true,"numPista":2}],"puertas":[{"numPuerta":1,"disponible":true,"companiaAerea":{"nombre":"AVIANCA"}},{"numPuerta":2,"disponible":true,"companiaAerea":{"nombre":"IBERIA"}},{"numPuerta":3,"disponible":true,"companiaAerea":{"nombre":"TACA"}},{"numPuerta":4,"disponible":true,"companiaAerea":{"nombre":"AVIANCA"}}],"nombre":"Juan Santamaría"},"companiaAerea":{"nombre":"Avianca"},"horaSalida":"11:57:47","horaLlegada":"01:57:53"},{"idVuelo":"VL96734","aeronave":{"placa":"123asdf","tipo":1,"COMERCIAL":1,"CARGA":2,"AVIONETA":3,"estado":1},"aeropuertoOrigen":{"nombre":"Aeropuerto de Hamburgo"},"aeropuertoDestino":{"pistas":[{"disponible":true,"numPista":1},{"disponible":true,"numPista":2}],"puertas":[{"numPuerta":1,"disponible":true,"companiaAerea":{"nombre":"AVIANCA"}},{"numPuerta":2,"disponible":true,"companiaAerea":{"nombre":"IBERIA"}},{"numPuerta":3,"disponible":true,"companiaAerea":{"nombre":"TACA"}},{"numPuerta":4,"disponible":true,"companiaAerea":{"nombre":"AVIANCA"}}],"nombre":"Juan Santamaría"},"companiaAerea":{"nombre":"Avianca"},"horaSalida":"11:57:47","horaLlegada":"01:57:56"},{"idVuelo":"VL04923","aeronave":{"placa":"12345afasdf","tipo":3,"COMERCIAL":1,"CARGA":2,"AVIONETA":3,"estado":3},"aeropuertoOrigen":{"nombre":"Aeropuerto Internacional Tobías Bolaños"},"aeropuertoDestino":{"pistas":[{"disponible":true,"numPista":1},{"disponible":true,"numPista":2}],"puertas":[{"numPuerta":1,"disponible":true,"companiaAerea":{"nombre":"AVIANCA"}},{"numPuerta":2,"disponible":true,"companiaAerea":{"nombre":"IBERIA"}},{"numPuerta":3,"disponible":true,"companiaAerea":{"nombre":"TACA"}},{"numPuerta":4,"disponible":true,"companiaAerea":{"nombre":"AVIANCA"}}],"nombre":"Juan Santamaría"},"companiaAerea":{"nombre":"Avianca"},"horaSalida":"03:04:14","horaLlegada":"02:04:41"},{"idVuelo":"VL04923","aeronave":{"placa":"12345afasdf","tipo":3,"COMERCIAL":1,"CARGA":2,"AVIONETA":3,"estado":1},"aeropuertoOrigen":{"nombre":"Aeropuerto Internacional Tobías Bolaños"},"aeropuertoDestino":{"pistas":[{"disponible":true,"numPista":1},{"disponible":true,"numPista":2}],"puertas":[{"numPuerta":1,"disponible":true,"companiaAerea":{"nombre":"AVIANCA"}},{"numPuerta":2,"disponible":true,"companiaAerea":{"nombre":"IBERIA"}},{"numPuerta":3,"disponible":true,"companiaAerea":{"nombre":"TACA"}},{"numPuerta":4,"disponible":true,"companiaAerea":{"nombre":"AVIANCA"}}],"nombre":"Juan Santamaría"},"companiaAerea":{"nombre":"Avianca"},"horaSalida":"03:04:14","horaLlegada":"02:04:45"},{"idVuelo":"VL04923","aeronave":{"placa":"12345afasdf","tipo":3,"COMERCIAL":1,"CARGA":2,"AVIONETA":3,"estado":1},"aeropuertoOrigen":{"nombre":"Aeropuerto Internacional Tobías Bolaños"},"aeropuertoDestino":{"pistas":[{"disponible":true,"numPista":1},{"disponible":true,"numPista":2}],"puertas":[{"numPuerta":1,"disponible":true,"companiaAerea":{"nombre":"AVIANCA"}},{"numPuerta":2,"disponible":true,"companiaAerea":{"nombre":"IBERIA"}},{"numPuerta":3,"disponible":true,"companiaAerea":{"nombre":"TACA"}},{"numPuerta":4,"disponible":true,"companiaAerea":{"nombre":"AVIANCA"}}],"nombre":"Juan Santamaría"},"companiaAerea":{"nombre":"Avianca"},"horaSalida":"03:04:14","horaLlegada":"02:04:46"},{"idVuelo":"VL04923","aeronave":{"placa":"asdf","tipo":1,"COMERCIAL":1,"CARGA":2,"AVIONETA":3,"estado":3},"aeropuertoOrigen":{"nombre":"Aeropuerto Internacional de Viena"},"aeropuertoDestino":{"pistas":[{"disponible":true,"numPista":1},{"disponible":true,"numPista":2}],"puertas":[{"numPuerta":1,"disponible":true,"companiaAerea":{"nombre":"AVIANCA"}},{"numPuerta":2,"disponible":true,"companiaAerea":{"nombre":"IBERIA"}},{"numPuerta":3,"disponible":true,"companiaAerea":{"nombre":"TACA"}},{"numPuerta":4,"disponible":true,"companiaAerea":{"nombre":"AVIANCA"}}],"nombre":"Juan Santamaría"},"companiaAerea":{"nombre":"Iberia"},"horaSalida":"04:11:15","horaLlegada":"02:11:19"},{"idVuelo":"VL97620","aeronave":{"placa":"sdf","tipo":1,"COMERCIAL":1,"CARGA":2,"AVIONETA":3,"estado":3},"aeropuertoOrigen":{"nombre":"Aeropuerto Internacional de San Francisco"},"aeropuertoDestino":{"pistas":[{"disponible":true,"numPista":1},{"disponible":true,"numPista":2}],"puertas":[{"numPuerta":1,"disponible":true,"companiaAerea":{"nombre":"AVIANCA"}},{"numPuerta":2,"disponible":true,"companiaAerea":{"nombre":"IBERIA"}},{"numPuerta":3,"disponible":true,"companiaAerea":{"nombre":"TACA"}},{"numPuerta":4,"disponible":true,"companiaAerea":{"nombre":"AVIANCA"}}],"nombre":"Juan Santamaría"},"companiaAerea":{"nombre":"Avianca"},"horaSalida":"21:14:08","horaLlegada":"02:14:14"},{"idVuelo":"VL52452","aeronave":{"placa":"fsd","tipo":3,"COMERCIAL":1,"CARGA":2,"AVIONETA":3,"estado":3},"aeropuertoOrigen":{"nombre":"Aeropuerto Internacional de San Francisco"},"aeropuertoDestino":{"pistas":[{"disponible":true,"numPista":1},{"disponible":true,"numPista":2}],"puertas":[{"numPuerta":1,"disponible":true,"companiaAerea":{"nombre":"AVIANCA"}},{"numPuerta":2,"disponible":true,"companiaAerea":{"nombre":"IBERIA"}},{"numPuerta":3,"disponible":true,"companiaAerea":{"nombre":"TACA"}},{"numPuerta":4,"disponible":true,"companiaAerea":{"nombre":"AVIANCA"}}],"nombre":"Juan Santamaría"},"companiaAerea":{"nombre":"Avianca"},"horaSalida":"09:15:31","horaLlegada":"02:15:41"},{"idVuelo":"VL43230","aeronave":{"placa":"sdf","tipo":3,"COMERCIAL":1,"CARGA":2,"AVIONETA":3,"estado":3},"aeropuertoOrigen":{"nombre":"Aeropuerto de Asheville"},"aeropuertoDestino":{"pistas":[{"disponible":true,"numPista":1},{"disponible":true,"numPista":2}],"puertas":[{"numPuerta":1,"disponible":true,"companiaAerea":{"nombre":"AVIANCA"}},{"numPuerta":2,"disponible":true,"companiaAerea":{"nombre":"IBERIA"}},{"numPuerta":3,"disponible":true,"companiaAerea":{"nombre":"TACA"}},{"numPuerta":4,"disponible":true,"companiaAerea":{"nombre":"AVIANCA"}}],"nombre":"Juan Santamaría"},"companiaAerea":{"nombre":"Iberia"},"horaSalida":"14:16:13","horaLlegada":"02:16:20"}]